{
  "status": "ok",
  "request_id": "req_demo_0002",
  "timestamp_ms": 1730000000000,
  "data": {
    "mode": "REPLY",
    "voice_match_score": 79,
    "risk": {
      "level": "yellow",
      "score": 42,
      "reasons": ["They feel stressed", "Boundary request is clear"]
    },
    "applied_contact": { "id": "contact_demo_01", "display_name": "Sara", "relation_tag": "partner" },
    "style_applied_summary": "Accountable, kamtar emoji, roshan",
    "suggestions": [
      {
        "label": "Accountable",
        "text": "Hagh dari. cancel kardan-e last minute dorost nabood. az in be bad age ehtemal-e taghir bashe zoodtar behet migam ta stress nagiri.",
        "why_it_works": "Validates their feeling and commits to a concrete change.",
        "emotion_preview": ["validated", "safe"]
      },
      {
        "label": "Short",
        "text": "Hagh dari. az in be bad zoodtar khabar midam 🙏",
        "why_it_works": "Simple + direct.",
        "emotion_preview": ["calm"]
      },
      {
        "label": "Collaborative",
        "text": "Kamelan mifahmam. doost daram ye rule bezarim: age ta felan saat ghat'i naboodam, haman moghe behet begam ke to ham betooni barname-rizi koni. ok-e?",
        "why_it_works": "Turns it into a shared plan.",
        "emotion_preview": ["teamwork"]
      }
    ]
  },
  "error": null,
  "meta": {
    "contract_version": "1.0.0"
  }
}